stix_shifter_modules/bigfix/__init__.py
stix_shifter_modules/bigfix/entry_point.py
stix_shifter_modules/bigfix/configuration/config.json
stix_shifter_modules/bigfix/configuration/dialects.json
stix_shifter_modules/bigfix/configuration/lang_en.json
stix_shifter_modules/bigfix/stix_translation/__init__.py
stix_shifter_modules/bigfix/stix_translation/json_to_stix_translator.py
stix_shifter_modules/bigfix/stix_translation/query_constructor.py
stix_shifter_modules/bigfix/stix_translation/query_translator.py
stix_shifter_modules/bigfix/stix_translation/json/from_stix_map.json
stix_shifter_modules/bigfix/stix_translation/json/operators.json
stix_shifter_modules/bigfix/stix_translation/json/relevance_property_format_string_map.json
stix_shifter_modules/bigfix/stix_translation/json/to_stix_map.json
stix_shifter_modules/bigfix/stix_translation/json/stix_2_1/from_stix_map.json
stix_shifter_modules/bigfix/stix_translation/json/stix_2_1/to_stix_map.json
stix_shifter_modules/bigfix/stix_transmission/__init__.py
stix_shifter_modules/bigfix/stix_transmission/api_client.py
stix_shifter_modules/bigfix/stix_transmission/delete_connector.py
stix_shifter_modules/bigfix/stix_transmission/error_mapper.py
stix_shifter_modules/bigfix/stix_transmission/ping_connector.py
stix_shifter_modules/bigfix/stix_transmission/query_connector.py
stix_shifter_modules/bigfix/stix_transmission/results_connector.py
stix_shifter_modules/bigfix/stix_transmission/status_connector.py
stix_shifter_modules_bigfix-8.0.2.dist-info/licenses/AUTHORS.md
stix_shifter_modules_bigfix-8.0.2.dist-info/licenses/LICENSE.md
stix_shifter_modules_bigfix-8.0.2.dist-info/licenses/NOTICE
stix_shifter_modules_bigfix-8.0.2.dist-info/METADATA
stix_shifter_modules_bigfix-8.0.2.dist-info/WHEEL
stix_shifter_modules_bigfix-8.0.2.dist-info/top_level.txt
stix_shifter_modules_bigfix-8.0.2.dist-info/RECORD
